ifilimu/__init__.py
ifilimu/main.py
ifilimu/utils.py
ifilimu-0.4.0.dist-info/licenses/LICENSE
ifilimu-0.4.0.dist-info/METADATA
ifilimu-0.4.0.dist-info/WHEEL
ifilimu-0.4.0.dist-info/top_level.txt
ifilimu-0.4.0.dist-info/RECORD
