Metadata-Version: 2.4
Name: ifilimu
Version: 0.4.0
Summary: Movie CLI to fetch and summarize movies
Author-email: Albert Niyonsenga <a.niyonseng@alustudent.com>
License: MIT
Requires-Python: >=3.12
License-File: LICENSE
Requires-Dist: httpx>=0.28.1
Requires-Dist: python-dotenv>=1.1.1
Requires-Dist: requests>=2.32.4
Requires-Dist: rich>=14.1.0
Requires-Dist: sqlite3
Requires-Dist: tenacity>=9.1.2
Requires-Dist: typer>=0.16.0
Dynamic: license-file
